{
  "minecraft:recipes/transportation/mangrove_boat": {
    "criteria": {
      "in_water": "2026-04-26 15:24:28 +0200"
    },
    "done": true
  },
  "minecraft:story/lava_bucket": {
    "criteria": {
      "lava_bucket": "2026-04-26 15:22:58 +0200"
    },
    "done": true
  },
  "minecraft:recipes/tools/flint_and_steel": {
    "criteria": {
      "has_obsidian": "2026-04-26 15:22:12 +0200"
    },
    "done": true
  },
  "minecraft:story/form_obsidian": {
    "criteria": {
      "obsidian": "2026-04-26 15:22:12 +0200"
    },
    "done": true
  },
  "minecraft:recipes/decorations/crafting_table": {
    "criteria": {
      "unlock_right_away": "2026-04-26 15:22:12 +0200"
    },
    "done": true
  },
  "minecraft:recipes/decorations/chest": {
    "criteria": {
      "has_lots_of_items": "2026-04-26 15:22:12 +0200"
    },
    "done": true
  },
  "minecraft:recipes/redstone/redstone_lamp": {
    "criteria": {
      "has_glowstone": "2026-04-26 15:22:12 +0200"
    },
    "done": true
  },
  "minecraft:recipes/brewing/cauldron": {
    "criteria": {
      "has_water_bucket": "2026-04-26 15:22:57 +0200"
    },
    "done": true
  },
  "minecraft:recipes/transportation/acacia_boat": {
    "criteria": {
      "in_water": "2026-04-26 15:24:28 +0200"
    },
    "done": true
  },
  "minecraft:recipes/transportation/cherry_boat": {
    "criteria": {
      "in_water": "2026-04-26 15:24:28 +0200"
    },
    "done": true
  },
  "minecraft:adventure/adventuring_time": {
    "criteria": {
      "minecraft:plains": "2026-04-26 15:22:39 +0200"
    },
    "done": false
  },
  "minecraft:recipes/transportation/bamboo_raft": {
    "criteria": {
      "in_water": "2026-04-26 15:24:28 +0200"
    },
    "done": true
  },
  "minecraft:recipes/redstone/redstone": {
    "criteria": {
      "has_redstone_block": "2026-04-26 15:22:12 +0200"
    },
    "done": true
  },
  "minecraft:recipes/transportation/spruce_boat": {
    "criteria": {
      "in_water": "2026-04-26 15:24:28 +0200"
    },
    "done": true
  },
  "minecraft:recipes/transportation/birch_boat": {
    "criteria": {
      "in_water": "2026-04-26 15:24:28 +0200"
    },
    "done": true
  },
  "minecraft:recipes/decorations/enchanting_table": {
    "criteria": {
      "has_obsidian": "2026-04-26 15:22:12 +0200"
    },
    "done": true
  },
  "minecraft:recipes/building_blocks/jack_o_lantern": {
    "criteria": {
      "has_carved_pumpkin": "2026-04-26 15:23:18 +0200"
    },
    "done": true
  },
  "minecraft:recipes/transportation/oak_boat": {
    "criteria": {
      "in_water": "2026-04-26 15:24:28 +0200"
    },
    "done": true
  },
  "minecraft:recipes/transportation/jungle_boat": {
    "criteria": {
      "in_water": "2026-04-26 15:24:28 +0200"
    },
    "done": true
  },
  "minecraft:recipes/food/pumpkin_pie": {
    "criteria": {
      "has_carved_pumpkin": "2026-04-26 15:23:18 +0200"
    },
    "done": true
  },
  "minecraft:recipes/transportation/dark_oak_boat": {
    "criteria": {
      "in_water": "2026-04-26 15:24:28 +0200"
    },
    "done": true
  },
  "DataVersion": 3465
}